{"version":1,"resource":"file:///home/alex/Development/rust/quiz-scoreboard/assets/css/style.css","entries":[{"id":"edJz.css","timestamp":1690897040565},{"id":"nOQ7.css","timestamp":1690897057995},{"id":"mo2f.css","timestamp":1690897288245},{"id":"HeO9.css","timestamp":1690897350879},{"id":"7uFA.css","timestamp":1690897440686},{"id":"P9Md.css","timestamp":1690897482523},{"id":"KZss.css","timestamp":1690897573448},{"id":"E8gE.css","timestamp":1690897590511},{"id":"tva0.css","timestamp":1690897602515},{"id":"JFRg.css","timestamp":1690897637328},{"id":"Zf9A.css","timestamp":1690897649725},{"id":"JQdF.css","timestamp":1690897670772},{"id":"ZLJF.css","timestamp":1690897722923},{"id":"9Ks6.css","timestamp":1690897747646},{"id":"g5qL.css","timestamp":1690897759110},{"id":"qDP7.css","source":"undoRedo.source","timestamp":1690897768917},{"id":"bM7H.css","timestamp":1690897819597},{"id":"zjNa.css","source":"undoRedo.source","timestamp":1690897822900},{"id":"KCkm.css","timestamp":1690897845817}]}